NewsFrames/__init__.py
NewsFrames/classifier.py
NewsFrames/config.py
NewsFrames-1.3.7.dist-info/LICENSE
NewsFrames-1.3.7.dist-info/METADATA
NewsFrames-1.3.7.dist-info/WHEEL
NewsFrames-1.3.7.dist-info/top_level.txt
NewsFrames-1.3.7.dist-info/RECORD
