Metadata-Version: 2.1
Name: NewsFrames
Version: 1.3.7
Summary: Easy-to-use, high-quality identification of generic framing dimensions in English news articles
Author-email: Felix Hamborg <felix.hamborg@hu-berlin.de>
Maintainer-email: Felix Hamborg <felix.hamborg@hu-berlin.de>
License: Apache License
Project-URL: Homepage, https://github.com/fhamborg/NewsFrames
Project-URL: Bug Reports, https://github.com/fhamborg/NewsFrames/issues
Keywords: news,articles,classification,bias,framing,frames,media
Classifier: Development Status :: 4 - Beta
Classifier: Intended Audience :: Developers
Classifier: Intended Audience :: Science/Research
Classifier: License :: OSI Approved :: Apache Software License
Classifier: Programming Language :: Python :: 3
Classifier: Programming Language :: Python :: 3.8
Classifier: Programming Language :: Python :: 3.9
Classifier: Programming Language :: Python :: 3.10
Classifier: Programming Language :: Python :: 3.11
Requires-Python: >=3.8
License-File: LICENSE
Requires-Dist: datasets <3.0.0,>=2
Requires-Dist: loguru
Requires-Dist: transformers[torch] <5.0.0,>=4
Requires-Dist: evaluate ==0.4.1
Requires-Dist: setfit ==0.7.0
Requires-Dist: scikit-learn ==1.3.0
Provides-Extra: cuda
Requires-Dist: cudatoolkit ==10.1 ; extra == 'cuda'
